globus_cli/__init__.py
globus_cli/__main__.py
globus_cli/_click_compat.py
globus_cli/_warnings.py
globus_cli/constants.py
globus_cli/globus_cli_flake8.py
globus_cli/reflect.py
globus_cli/types.py
globus_cli/utils.py
globus_cli/version.py
globus_cli/commands/__init__.py
globus_cli/commands/_common.py
globus_cli/commands/_removal_stub.py
globus_cli/commands/api.py
globus_cli/commands/cli_profile_list.py
globus_cli/commands/delete.py
globus_cli/commands/get_identities.py
globus_cli/commands/list_commands.py
globus_cli/commands/login.py
globus_cli/commands/logout.py
globus_cli/commands/ls.py
globus_cli/commands/mkdir.py
globus_cli/commands/rename.py
globus_cli/commands/rm.py
globus_cli/commands/stat.py
globus_cli/commands/transfer.py
globus_cli/commands/update.py
globus_cli/commands/version.py
globus_cli/commands/whoami.py
globus_cli/commands/bookmark/__init__.py
globus_cli/commands/bookmark/_common.py
globus_cli/commands/bookmark/create.py
globus_cli/commands/bookmark/delete.py
globus_cli/commands/bookmark/list.py
globus_cli/commands/bookmark/rename.py
globus_cli/commands/bookmark/show.py
globus_cli/commands/collection/__init__.py
globus_cli/commands/collection/_common.py
globus_cli/commands/collection/delete.py
globus_cli/commands/collection/list.py
globus_cli/commands/collection/show.py
globus_cli/commands/collection/update.py
globus_cli/commands/collection/create/__init__.py
globus_cli/commands/collection/create/guest.py
globus_cli/commands/collection/create/mapped.py
globus_cli/commands/collection/role/__init__.py
globus_cli/commands/collection/role/delete.py
globus_cli/commands/collection/role/list.py
globus_cli/commands/collection/role/show.py
globus_cli/commands/endpoint/__init__.py
globus_cli/commands/endpoint/_common.py
globus_cli/commands/endpoint/delete.py
globus_cli/commands/endpoint/local_id.py
globus_cli/commands/endpoint/my_shared_endpoint_list.py
globus_cli/commands/endpoint/search.py
globus_cli/commands/endpoint/set_subscription_id.py
globus_cli-3.40.0.dist-info/licenses/LICENSE
globus_cli-3.40.0.dist-info/METADATA
globus_cli-3.40.0.dist-info/WHEEL
globus_cli-3.40.0.dist-info/entry_points.txt
globus_cli-3.40.0.dist-info/top_level.txt
globus_cli-3.40.0.dist-info/RECORD
