Metadata-Version: 2.4
Name: globus-cli
Version: 3.40.0
Summary: Globus CLI
Author-email: Stephen Rosen <sirosen@globus.org>
License-Expression: Apache-2.0
Project-URL: homepage, https://github.com/globus/globus-cli
Keywords: globus,cli,command line
Classifier: Development Status :: 5 - Production/Stable
Classifier: Intended Audience :: Developers
Classifier: Operating System :: POSIX
Classifier: Programming Language :: Python
Classifier: Programming Language :: Python :: 3.9
Classifier: Programming Language :: Python :: 3.10
Classifier: Programming Language :: Python :: 3.11
Classifier: Programming Language :: Python :: 3.12
Classifier: Programming Language :: Python :: 3.13
Requires-Python: >=3.9
License-File: LICENSE
Requires-Dist: globus-sdk==4.1.0
Requires-Dist: click<8.4,>=8.1.4
Requires-Dist: jmespath==1.0.1
Requires-Dist: packaging>=17.0
Requires-Dist: typing_extensions>=4.0; python_version < "3.11"
Requires-Dist: requests<3.0.0,>=2.32.3
Dynamic: license-file
